CHANGES.md
MANIFEST.in
Makefile
README.rst
setup.cfg
setup.py
redis_session_backend/__init__.py
redis_session_backend/backends.py
redis_session_backend.egg-info/PKG-INFO
redis_session_backend.egg-info/SOURCES.txt
redis_session_backend.egg-info/dependency_links.txt
redis_session_backend.egg-info/requires.txt
redis_session_backend.egg-info/top_level.txt